{"parameters": {"input_shape": [128, 336, 21, 21], "output_shape": [128, 336, 21, 21], "window_shape": [3, 3], "window_stride": [1, 1], "padding_below": [1, 1]}, "op_type": "AvgPool", "tvm_func_name": "roller_AvgPool__128_336_21_21___128_336_21_21_", "code": "extern \"C\" __global__ void roller_AvgPool__128_336_21_21___128_336_21_21_(float* __restrict__ Pool2d, float* __restrict__ data) {\n  __shared__ float compute_shared[322];\n  if ((((((int)blockIdx.x) & 1) * 12) + (((int)threadIdx.x) / 24)) < 21) {\n    if ((((int)threadIdx.x) % 24) < 21) {\n      Pool2d[((((((((int)blockIdx.x) >> 1) * 441) + ((((int)blockIdx.x) & 1) * 252)) + ((((int)threadIdx.x) / 24) * 21)) + (((int)threadIdx.x) % 24)))] = 0.000000e+00f;\n    }\n  }\n  if ((((((int)blockIdx.x) & 1) * 12) + (((int)threadIdx.x) / 23)) < 23) {\n    compute_shared[(((int)threadIdx.x))] = (((((1 <= (((((int)blockIdx.x) & 1) * 12) + (((int)threadIdx.x) / 23))) && ((((((int)blockIdx.x) & 1) * 12) + (((int)threadIdx.x) / 23)) < 22)) && (1 <= (((int)threadIdx.x) % 23))) && ((((int)threadIdx.x) % 23) < 22)) ? data[((((((((int)blockIdx.x) >> 1) * 441) + ((((int)blockIdx.x) & 1) * 252)) + ((((int)threadIdx.x) / 23) * 21)) + (((int)threadIdx.x) % 23)))] : 0.000000e+00f);\n  }\n  if (((int)threadIdx.x) < 34) {\n    if ((((((int)blockIdx.x) & 1) * 12) + ((((int)threadIdx.x) + 288) / 23)) < 23) {\n      compute_shared[((((int)threadIdx.x) + 288))] = (((((((((int)blockIdx.x) & 1) * 12) + ((((int)threadIdx.x) + 288) / 23)) < 22) && (1 <= ((((int)threadIdx.x) + 12) % 23))) && (((((int)threadIdx.x) + 12) % 23) < 22)) ? data[((((((((int)blockIdx.x) >> 1) * 441) + ((((int)blockIdx.x) & 1) * 252)) + (((((int)threadIdx.x) + 288) / 23) * 21)) + ((((int)threadIdx.x) + 12) % 23)))] : 0.000000e+00f);\n    }\n  }\n  __syncthreads();\n  for (int k_inner_outer = 0; k_inner_outer < 9; ++k_inner_outer) {\n    if ((((((int)blockIdx.x) & 1) * 12) + (((int)threadIdx.x) / 24)) < 21) {\n      if ((((int)threadIdx.x) % 24) < 21) {\n        Pool2d[((((((((int)blockIdx.x) >> 1) * 441) + ((((int)blockIdx.x) & 1) * 252)) + ((((int)threadIdx.x) / 24) * 21)) + (((int)threadIdx.x) % 24)))] = (Pool2d[((((((((int)blockIdx.x) >> 1) * 441) + ((((int)blockIdx.x) & 1) * 252)) + ((((int)threadIdx.x) / 24) * 21)) + (((int)threadIdx.x) % 24)))] + (compute_shared[((((((((int)threadIdx.x) / 24) * 23) + ((k_inner_outer / 3) * 23)) + (((int)threadIdx.x) % 24)) + (k_inner_outer % 3)))] * 1.111111e-01f));\n      }\n    }\n  }\n}\n", "gridDim": [86016, 1, 1], "blockDim": [288, 1, 1]}